featurebase/__init__.py
featurebase/client.py
featurebase-0.1.0.dist-info/METADATA
featurebase-0.1.0.dist-info/WHEEL
featurebase-0.1.0.dist-info/RECORD
