Metadata-Version: 2.1
Name: featurebase
Version: 0.1.0
Summary: A client library for Featurebase.
Project-URL: Homepage, https://github.com/molecula/python-featurebase
Project-URL: Bug Tracker, https://github.com/molecula/python-featurebase/issues
Author-email: Featurebase Developers <dev@featurebase.com>
Classifier: Intended Audience :: Developers
Classifier: License :: OSI Approved :: MIT License
Classifier: Operating System :: OS Independent
Classifier: Programming Language :: Python :: 3
Requires-Python: >=3.7
